{
  "status": 1,
  "msg": "",
  "data": [
    {
      "id": 0,
      "title": "法拉利FF美女车模冯靖媛性感写真高清壁纸",
      "thumbSmall": "https://raw.githubusercontent.com/nalala1314/nalala1314.github.io/master/intube/resources/car_model/5/00.webp",
      "header": {
        "Referer": "https://nalala1314.github.io/"
      },
      "parentUrl": "https://raw.githubusercontent.com/nalala1314/nalala1314.github.io/master/intube/resources/car_model/5/",
      "source": "https://www.5442.com/qiche/20170410/43287.html",
      "urls": [
        "1.webp",
        "2.webp",
        "3.webp",
        "4.webp",
        "5.webp",
        "6.webp"
      ]
    },
    {
      "id": 12,
      "title": "奥迪A7性感美腿车模高清壁纸5",
      "thumbSmall": "https://raw.githubusercontent.com/nalala1314/nalala1314.github.io/master/intube/resources/car_model/1/00.webp",
      "header": {
        "Referer": "https://nalala1314.github.io/"
      },
      "parentUrl": "https://raw.githubusercontent.com/nalala1314/nalala1314.github.io/master/intube/resources/car_model/1/",
      "source": "http://www.xiazaizhijia.com/bizhi/8654.html",
      "urls": [
        "1.webp",
        "2.webp",
        "3.webp",
        "4.webp",
        "5.webp",
        "6.webp"
      ]
    },
    {
      "id": 1,
      "title": "大胸模特车模美女惊艳写真",
      "thumbSmall": "https://raw.githubusercontent.com/nalala1314/nalala1314.github.io/master/intube/resources/car_model/2/00.webp",
      "header": {
        "Referer": "https://nalala1314.github.io/"
      },
      "parentUrl": "https://raw.githubusercontent.com/nalala1314/nalala1314.github.io/master/intube/resources/car_model/2/",
      "urls": [
        "1.webp",
        "2.webp",
        "3.webp"
      ]
    },
    {
      "id": 1,
      "title": "韩国超级车模许允美展台可爱摄影图片",
      "thumbSmall": "https://raw.githubusercontent.com/nalala1314/nalala1314.github.io/master/intube/resources/car_model/3/00.webp",
      "header": {
        "Referer": "https://nalala1314.github.io/"
      },
      "source": "https://www.uumtu.com/chemo/22021.html",
      "parentUrl": "https://raw.githubusercontent.com/nalala1314/nalala1314.github.io/master/intube/resources/car_model/3/",
      "urls": [
        "1.webp",
        "2.webp",
        "3.webp",
        "4.webp",
        "5.webp",
        "6.webp",
        "7.webp"
      ]
    },
    {
      "id": 2,
      "title": "中国车模美女修长美腿高跟鞋写真图片",
      "thumbSmall": "https://raw.githubusercontent.com/nalala1314/nalala1314.github.io/master/intube/resources/car_model/4/00.webp",
      "header": {
        "Referer": "https://nalala1314.github.io/"
      },
      "source": "https://www.uumtu.com/chemo/22332.html",
      "parentUrl": "https://raw.githubusercontent.com/nalala1314/nalala1314.github.io/master/intube/resources/car_model/4/",
      "urls": [
        "1.webp",
        "2.webp",
        "3.webp",
        "4.webp"
      ]
    }
  ]
}
